pooled/__init__.py
pooled/pooled.py
pooled-0.0.1.dist-info/LICENSE
pooled-0.0.1.dist-info/METADATA
pooled-0.0.1.dist-info/WHEEL
pooled-0.0.1.dist-info/top_level.txt
pooled-0.0.1.dist-info/RECORD
